{
  "month": "MARCH",
  "days": [
    {
      "name": "TUESDAY",
      "date": 1,
      "highlight": false,
      "sessions": [
        {
          "id": "tuesday-1-68",
          "startTime": "6:30 AM",
          "endTime": "8:00 AM",
          "title": "Pickleball Open Play: All Levels Drill Session: Bring Your Own Partner",
          "subtitle": "Skill Level: All Levels",
          "location": "Indoor Pickleball Courts"
        },
        {
          "id": "tuesday-1-69",
          "startTime": "6:30 AM",
          "endTime": "8:00 AM",
          "title": "Pickleball Open Play: All Levels DUPR Optional (4on/4off)",
          "subtitle": "Skill Level: All Levels",
          "location": "Indoor Pickleball Courts"
        },
        {
          "id": "tuesday-1-70",
          "startTime": "8:00 AM",
          "endTime": "9:30 AM",
          "title": "Pickleball Open Play: All Levels (4on4off) DUPR Optional",
          "subtitle": "Skill Level: All Levels",
          "location": "Indoor Pickleball Courts"
        },
        {
          "id": "tuesday-1-71",
          "startTime": "8:00 AM",
          "endTime": "9:30 AM",
          "title": "Pickleball Open Play: All Levels Drill Session: Bring Your Own Partner",
          "subtitle": "Skill Level: All Levels",
          "location": "Indoor Pickleball Courts"
        },
        {
          "id": "tuesday-1-72",
          "startTime": "9:30 AM",
          "endTime": "11:30 AM",
          "title": "Pickleball Open Play: 3.0-3.75 DUPR Optional",
          "subtitle": "Skill Level: 3.0-",
          "location": "Indoor Pickleball Courts"
        },
        {
          "id": "tuesday-1-73",
          "startTime": "9:30 AM",
          "endTime": "11:30 AM",
          "title": "Pickleball Open Play: 3.75-4.25 DUPR Optional",
          "subtitle": "Skill Level: 3.75-",
          "location": "Indoor Pickleball Courts"
        },
        {
          "id": "tuesday-1-74",
          "startTime": "9:30 AM",
          "endTime": "11:30 AM",
          "title": "Pickleball Open Play: 4.25+ DUPR Optional",
          "subtitle": "Skill Level: 4.25+",
          "location": "Indoor Pickleball Courts"
        },
        {
          "id": "tuesday-1-75",
          "startTime": "9:30 AM",
          "endTime": "11:30 AM",
          "title": "Pickleball Open Play: Womens 2.0+ DUPR Optional",
          "subtitle": "Skill Level: 2.0+",
          "location": "Indoor Pickleball Courts"
        },
        {
          "id": "tuesday-1-76",
          "startTime": "10:00 AM",
          "endTime": "11:30 AM",
          "title": "Pickleball Open Play: 4.0+ Drill Session: Bring Your Own Partner",
          "subtitle": "Skill Level: 4.0+",
          "location": "Indoor Pickleball Courts"
        },
        {
          "id": "tuesday-1-77",
          "startTime": "11:30 AM",
          "endTime": "1:30 PM",
          "title": "Pickleball Open Play: 3.75-4.25 DUPR Optional",
          "subtitle": "Skill Level: 3.75-",
          "location": "Indoor Pickleball Courts"
        },
        {
          "id": "tuesday-1-78",
          "startTime": "11:30 AM",
          "endTime": "1:30 PM",
          "title": "Pickleball Open Play: All Levels DUPR Optional - 4 on/off",
          "subtitle": "Skill Level: All Levels",
          "location": "Indoor Pickleball Courts"
        },
        {
          "id": "tuesday-1-79",
          "startTime": "11:30 AM",
          "endTime": "1:30 PM",
          "title": "Pickleball Open Play: NR/2.0-3.0 DUPR Optional",
          "subtitle": "Skill Level: 2.0-",
          "location": "Indoor Pickleball Courts"
        },
        {
          "id": "tuesday-1-80",
          "startTime": "11:30 AM",
          "endTime": "1:30 PM",
          "title": "Pickleball Open Play: Womens 3.0+ DUPR Optional",
          "subtitle": "Skill Level: 3.0+",
          "location": "Indoor Pickleball Courts"
        },
        {
          "id": "tuesday-1-81",
          "startTime": "12:30 PM",
          "endTime": "2:00 PM",
          "title": "Pickleball Open Play: 4.7+ Drill/Play",
          "subtitle": "Skill Level: 4.7+",
          "location": "Indoor Pickleball Courts"
        },
        {
          "id": "tuesday-1-82",
          "startTime": "12:30 PM",
          "endTime": "2:00 PM",
          "title": "Pickleball Open Play: 5.0+ Drill Session BYOP",
          "subtitle": "Skill Level: 5.0+",
          "location": "Indoor Pickleball Courts"
        },
        {
          "id": "tuesday-1-83",
          "startTime": "1:30 PM",
          "endTime": "3:00 PM",
          "title": "Pickleball Open Play: 2.75+ DUPR Optional",
          "subtitle": "Skill Level: 2.75+",
          "location": "Indoor Pickleball Courts"
        },
        {
          "id": "tuesday-1-84",
          "startTime": "1:30 PM",
          "endTime": "3:00 PM",
          "title": "Pickleball Open Play: All Levels Drill Session: Bring Your Own Partner",
          "subtitle": "Skill Level: All Levels",
          "location": "Indoor Pickleball Courts"
        },
        {
          "id": "tuesday-1-85",
          "startTime": "1:30 PM",
          "endTime": "3:30 PM",
          "title": "Pickleball Open Play: 4.0+ DUPR Optional",
          "subtitle": "Skill Level: 4.0+",
          "location": "Indoor Pickleball Courts"
        },
        {
          "id": "tuesday-1-86",
          "startTime": "2:00 PM",
          "endTime": "3:30 PM",
          "title": "Pickleball Open Play: All Levels DUPR Optional - 4 on/off",
          "subtitle": "Skill Level: All Levels",
          "location": "Indoor Pickleball Courts"
        },
        {
          "id": "tuesday-1-87",
          "startTime": "3:00 PM",
          "endTime": "5:00 PM",
          "title": "Pickleball Open Play: 2.0-3.0 DUPR Optional",
          "subtitle": "Skill Level: 2.0-",
          "location": "Indoor Pickleball Courts"
        },
        {
          "id": "tuesday-1-88",
          "startTime": "3:00 PM",
          "endTime": "5:00 PM",
          "title": "Pickleball Open Play: 3.0-3.75 DUPR Optional",
          "subtitle": "Skill Level: 3.0-",
          "location": "Indoor Pickleball Courts"
        },
        {
          "id": "tuesday-1-89",
          "startTime": "3:30 PM",
          "endTime": "5:00 PM",
          "title": "Pickleball Open Play: 4.0-4.5 (80%+ Reliability Required) DUPR Optional",
          "subtitle": "Skill Level: 4.0-",
          "location": "Indoor Pickleball Courts"
        },
        {
          "id": "tuesday-1-90",
          "startTime": "3:30 PM",
          "endTime": "5:30 PM",
          "title": "Pickleball Open Play: 3.75+ (80%+ Reliability Required) DUPR Optional",
          "subtitle": "Skill Level: 3.75+",
          "location": "Indoor Pickleball Courts"
        },
        {
          "id": "tuesday-1-91",
          "startTime": "3:30 PM",
          "endTime": "5:30 PM",
          "title": "Pickleball Open Play: 4.5+ DUPR Optional",
          "subtitle": "Skill Level: 4.5+",
          "location": "Indoor Pickleball Courts"
        },
        {
          "id": "tuesday-1-92",
          "startTime": "5:00 PM",
          "endTime": "6:30 PM",
          "title": "Pickleball Open Play: 3.0-3.5 DUPR Mandatory: Club Submit",
          "subtitle": "Skill Level: 3.0-",
          "location": "Indoor Pickleball Courts"
        },
        {
          "id": "tuesday-1-93",
          "startTime": "5:00 PM",
          "endTime": "6:30 PM",
          "title": "Pickleball Open Play: 3.5-4.0 (80%+ Reliability Required) DUPR Optional",
          "subtitle": "Skill Level: 3.5-",
          "location": "Indoor Pickleball Courts"
        },
        {
          "id": "tuesday-1-94",
          "startTime": "5:00 PM",
          "endTime": "6:30 PM",
          "title": "Pickleball Open Play: 4.0-4.5 DUPR Mandatory: Club Submit",
          "subtitle": "Skill Level: 4.0-",
          "location": "Indoor Pickleball Courts"
        },
        {
          "id": "tuesday-1-95",
          "startTime": "5:30 PM",
          "endTime": "7:00 PM",
          "title": "Pickleball Open Play: 3.5-4.0 DUPR Mandatory",
          "subtitle": "Skill Level: 3.5-",
          "location": "Indoor Pickleball Courts"
        },
        {
          "id": "tuesday-1-96",
          "startTime": "5:30 PM",
          "endTime": "7:30 PM",
          "title": "Pickleball Open Play: Womens 3.5+ (80% Reliability) DUPR Optional",
          "subtitle": "Skill Level: 3.5+",
          "location": "Indoor Pickleball Courts"
        },
        {
          "id": "tuesday-1-97",
          "startTime": "6:30 PM",
          "endTime": "8:00 PM",
          "title": "Pickleball Open Play: 3.75-4.25 DUPR Mandatory: Club Submit",
          "subtitle": "Skill Level: 3.75-",
          "location": "Indoor Pickleball Courts"
        },
        {
          "id": "tuesday-1-98",
          "startTime": "6:30 PM",
          "endTime": "8:00 PM",
          "title": "Pickleball Open Play: NR/2.0-2.75 DUPR Mandatory: Club Submit",
          "subtitle": "Skill Level: 2.0-",
          "location": "Indoor Pickleball Courts"
        },
        {
          "id": "tuesday-1-99",
          "startTime": "7:00 PM",
          "endTime": "9:00 PM",
          "title": "Pickleball Open Play: 3.75+ (80%+ Reliability Required) DUPR Optional",
          "subtitle": "Skill Level: 3.75+",
          "location": "Indoor Pickleball Courts"
        },
        {
          "id": "tuesday-1-100",
          "startTime": "7:30 PM",
          "endTime": "9:30 PM",
          "title": "Pickleball Open Play: 5.0+ DUPR Optional",
          "subtitle": "Skill Level: 5.0+",
          "location": "Indoor Pickleball Courts"
        },
        {
          "id": "tuesday-1-101",
          "startTime": "8:00 PM",
          "endTime": "10:00 PM",
          "title": "Pickleball Open Play: 2.75-3.25 DUPR Mandatory: Club Submit",
          "subtitle": "Skill Level: 2.75-",
          "location": "Indoor Pickleball Courts"
        },
        {
          "id": "tuesday-1-102",
          "startTime": "8:00 PM",
          "endTime": "10:00 PM",
          "title": "Pickleball Open Play: 3.25-3.75 BYOP (Combine <7.6) DUPR Mandatory: Club Submit (Partners Stay)",
          "subtitle": "Skill Level: 3.25-",
          "location": "Indoor Pickleball Courts"
        },
        {
          "id": "tuesday-1-103",
          "startTime": "8:30 PM",
          "endTime": "10:00 PM",
          "title": "Pickleball Open Play: 4.25-4.75 DUPR Optional",
          "subtitle": "Skill Level: 4.25-",
          "location": "Indoor Pickleball Courts"
        },
        {
          "id": "tuesday-1-104",
          "startTime": "9:00 PM",
          "endTime": "10:30 PM",
          "title": "Pickleball Open Play: 2.0-3.0 DUPR Mandatory: Club Submit",
          "subtitle": "Skill Level: 2.0-",
          "location": "Indoor Pickleball Courts"
        },
        {
          "id": "tuesday-1-105",
          "startTime": "9:30 PM",
          "endTime": "11:30 PM",
          "title": "Pickleball Open Play: 4.5+ DUPR Optional",
          "subtitle": "Skill Level: 4.5+",
          "location": "Indoor Pickleball Courts"
        },
        {
          "id": "tuesday-1-106",
          "startTime": "10:00 PM",
          "endTime": "11:30 PM",
          "title": "Pickleball Open Play",
          "location": "Indoor Pickleball Courts"
        },
        {
          "id": "tuesday-1-107",
          "startTime": "10:00 PM",
          "endTime": "11:30 PM",
          "title": "Pickleball Open Play: 4.0+ DUPR Optional",
          "subtitle": "Skill Level: 4.0+",
          "location": "Indoor Pickleball Courts"
        },
        {
          "id": "tuesday-1-108",
          "startTime": "10:30 PM",
          "endTime": "11:59 PM",
          "title": "Pickleball Open Play: 3.0+ DUPR Optional",
          "subtitle": "Skill Level: 3.0+",
          "location": "Indoor Pickleball Courts"
        }
      ],
      "header": "TUESDAY 1"
    },
    {
      "name": "WEDNESDAY",
      "date": 2,
      "highlight": false,
      "sessions": [
        {
          "id": "wednesday-2-109",
          "startTime": "6:30 AM",
          "endTime": "8:00 AM",
          "title": "Pickleball Open Play: 3.0+ DUPR Optional",
          "subtitle": "Skill Level: 3.0+",
          "location": "Indoor Pickleball Courts"
        },
        {
          "id": "wednesday-2-110",
          "startTime": "6:30 AM",
          "endTime": "8:00 AM",
          "title": "Pickleball Open Play: All Levels Drill Session: Bring Your Own Partner",
          "subtitle": "Skill Level: All Levels",
          "location": "Indoor Pickleball Courts"
        },
        {
          "id": "wednesday-2-111",
          "startTime": "7:00 AM",
          "endTime": "9:00 AM",
          "title": "Pickleball Open Play: Womens 3.75+ DUPR Optional",
          "subtitle": "Skill Level: 3.75+",
          "location": "Indoor Pickleball Courts"
        },
        {
          "id": "wednesday-2-112",
          "startTime": "8:00 AM",
          "endTime": "9:30 AM",
          "title": "Pickleball Open Play: All Levels Drill Session: Bring Your Own Partner",
          "subtitle": "Skill Level: All Levels",
          "location": "Indoor Pickleball Courts"
        },
        {
          "id": "wednesday-2-113",
          "startTime": "8:00 AM",
          "endTime": "9:30 AM",
          "title": "Pickleball Open Play: All Levels DUPR Optional",
          "subtitle": "Skill Level: All Levels",
          "location": "Indoor Pickleball Courts"
        },
        {
          "id": "wednesday-2-114",
          "startTime": "9:00 AM",
          "endTime": "10:30 AM",
          "title": "Pickleball Open Play: 4.25+ Drill Session: Bring Your Own Partner",
          "subtitle": "Skill Level: 4.25+",
          "location": "Indoor Pickleball Courts"
        },
        {
          "id": "wednesday-2-115",
          "startTime": "9:30 AM",
          "endTime": "11:30 AM",
          "title": "Pickleball Open Play: 3.75-4.25 DUPR Optional",
          "subtitle": "Skill Level: 3.75-",
          "location": "Indoor Pickleball Courts"
        },
        {
          "id": "wednesday-2-116",
          "startTime": "9:30 AM",
          "endTime": "11:30 AM",
          "title": "Pickleball Open Play: 4.0+ DUPR Optional",
          "subtitle": "Skill Level: 4.0+",
          "location": "Indoor Pickleball Courts"
        },
        {
          "id": "wednesday-2-117",
          "startTime": "9:30 AM",
          "endTime": "11:30 AM",
          "title": "Pickleball Open Play: Womens 2.0+ DUPR Optional",
          "subtitle": "Skill Level: 2.0+",
          "location": "Indoor Pickleball Courts"
        },
        {
          "id": "wednesday-2-118",
          "startTime": "10:00 AM",
          "endTime": "12:00 PM",
          "title": "Pickleball Open Play: 3.0-3.75 DUPR Optional",
          "subtitle": "Skill Level: 3.0-",
          "location": "Indoor Pickleball Courts"
        },
        {
          "id": "wednesday-2-119",
          "startTime": "10:30 AM",
          "endTime": "12:30 PM",
          "title": "Pickleball Open Play: 3.5-4.0 DUPR Optional",
          "subtitle": "Skill Level: 3.5-",
          "location": "Indoor Pickleball Courts"
        },
        {
          "id": "wednesday-2-120",
          "startTime": "10:30 AM",
          "endTime": "12:30 PM",
          "title": "Pickleball Open Play: 4.25+DUPR Optional",
          "subtitle": "Skill Level: 4.25+",
          "location": "Indoor Pickleball Courts"
        },
        {
          "id": "wednesday-2-121",
          "startTime": "11:30 AM",
          "endTime": "1:30 PM",
          "title": "Pickleball Open Play: 3.75-4.25 DUPR Optional",
          "subtitle": "Skill Level: 3.75-",
          "location": "Indoor Pickleball Courts"
        },
        {
          "id": "wednesday-2-122",
          "startTime": "11:30 AM",
          "endTime": "1:30 PM",
          "title": "Pickleball Open Play: All Levels (4on4off) DUPR Optional",
          "subtitle": "Skill Level: All Levels",
          "location": "Indoor Pickleball Courts"
        },
        {
          "id": "wednesday-2-123",
          "startTime": "12:00 PM",
          "endTime": "2:00 PM",
          "title": "Pickleball Open Play: 4.75+ DUPR Optional",
          "subtitle": "Skill Level: 4.75+",
          "location": "Indoor Pickleball Courts"
        },
        {
          "id": "wednesday-2-124",
          "startTime": "12:30 PM",
          "endTime": "2:30 PM",
          "title": "Pickleball Open Play: All Levels (4on4off) DUPR Optional",
          "subtitle": "Skill Level: All Levels",
          "location": "Indoor Pickleball Courts"
        },
        {
          "id": "wednesday-2-125",
          "startTime": "1:30 PM",
          "endTime": "3:00 PM",
          "title": "Pickleball Open Play: 3.5+ Drill Session. Please bring a partner",
          "subtitle": "Skill Level: 3.5+",
          "location": "Indoor Pickleball Courts"
        },
        {
          "id": "wednesday-2-126",
          "startTime": "1:30 PM",
          "endTime": "3:30 PM",
          "title": "Pickleball Open Play: 4.25-4.75 DUPR Optional",
          "subtitle": "Skill Level: 4.25-",
          "location": "Indoor Pickleball Courts"
        },
        {
          "id": "wednesday-2-127",
          "startTime": "1:30 PM",
          "endTime": "3:30 PM",
          "title": "Pickleball Open Play: Womens All Levels DUPR Optional",
          "subtitle": "Skill Level: All Levels",
          "location": "Indoor Pickleball Courts"
        },
        {
          "id": "wednesday-2-128",
          "startTime": "2:00 PM",
          "endTime": "4:00 PM",
          "title": "Pickleball Open Play: 3.25+ (80% Reliability )DUPR Optional",
          "subtitle": "Skill Level: 3.25+",
          "location": "Indoor Pickleball Courts"
        },
        {
          "id": "wednesday-2-129",
          "startTime": "2:30 PM",
          "endTime": "4:30 PM",
          "title": "Pickleball Open Play: All Levels DUPR Optional (4on/4off)",
          "subtitle": "Skill Level: All Levels",
          "location": "Indoor Pickleball Courts"
        },
        {
          "id": "wednesday-2-130",
          "startTime": "3:00 PM",
          "endTime": "4:30 PM",
          "title": "Pickleball Open Play: 4.25+ DUPR Optional",
          "subtitle": "Skill Level: 4.25+",
          "location": "Indoor Pickleball Courts"
        },
        {
          "id": "wednesday-2-131",
          "startTime": "3:30 PM",
          "endTime": "5:30 PM",
          "title": "Pickleball Open Play: 3.75-4.25 (80%+ Reliability Required)DUPR Optional",
          "subtitle": "Skill Level: 3.75-",
          "location": "Indoor Pickleball Courts"
        },
        {
          "id": "wednesday-2-132",
          "startTime": "4:00 PM",
          "endTime": "6:00 PM",
          "title": "Pickleball Open Play: 3.5-4.0 DUPR Optional",
          "subtitle": "Skill Level: 3.5-",
          "location": "Indoor Pickleball Courts"
        },
        {
          "id": "wednesday-2-133",
          "startTime": "4:30 PM",
          "endTime": "6:30 PM",
          "title": "Pickleball Open Play: 4.0-4.5 (80%+ Reliability Required) DUPR Optional",
          "subtitle": "Skill Level: 4.0-",
          "location": "Indoor Pickleball Courts"
        },
        {
          "id": "wednesday-2-134",
          "startTime": "5:30 PM",
          "endTime": "7:30 PM",
          "title": "Pickleball Open Play: 3.25-3.75 Womens  (80%+ Reliability Required) DUPR Optional",
          "subtitle": "Skill Level: 3.25-",
          "location": "Indoor Pickleball Courts"
        },
        {
          "id": "wednesday-2-135",
          "startTime": "6:00 PM",
          "endTime": "8:00 PM",
          "title": "Pickleball Open Play: 4.75+ (80%+ Reliability Required) DUPR Optional",
          "subtitle": "Skill Level: 4.75+",
          "location": "Indoor Pickleball Courts"
        },
        {
          "id": "wednesday-2-136",
          "startTime": "6:30 PM",
          "endTime": "8:00 PM",
          "title": "Pickleball Open Play: 2.5-3.0 DUPR Optional",
          "subtitle": "Skill Level: 2.5-",
          "location": "Indoor Pickleball Courts"
        },
        {
          "id": "wednesday-2-137",
          "startTime": "6:30 PM",
          "endTime": "8:00 PM",
          "title": "Pickleball Open Play: 3.75-4.25 (80%+ Reliability Required) DUPR Optional",
          "subtitle": "Skill Level: 3.75-",
          "location": "Indoor Pickleball Courts"
        },
        {
          "id": "wednesday-2-138",
          "startTime": "6:30 PM",
          "endTime": "8:30 PM",
          "title": "Pickleball Open Play: 4.25-4.75 (80%+ Reliability Required) DUPR Optional",
          "subtitle": "Skill Level: 4.25-",
          "location": "Indoor Pickleball Courts"
        },
        {
          "id": "wednesday-2-139",
          "startTime": "7:30 PM",
          "endTime": "9:30 PM",
          "title": "Pickleball Open Play: 3.5-4.0 (80%+ Reliability Required) DUPR Optional",
          "subtitle": "Skill Level: 3.5-",
          "location": "Indoor Pickleball Courts"
        },
        {
          "id": "wednesday-2-140",
          "startTime": "8:00 PM",
          "endTime": "9:30 PM",
          "title": "Pickleball Open Play: 3.0-3.5 DUPR Mandatory: Club Submit",
          "subtitle": "Skill Level: 3.0-",
          "location": "Indoor Pickleball Courts"
        },
        {
          "id": "wednesday-2-141",
          "startTime": "8:00 PM",
          "endTime": "9:30 PM",
          "title": "Pickleball Open Play: 4.5+ DUPR Mandatory",
          "subtitle": "Skill Level: 4.5+",
          "location": "Indoor Pickleball Courts"
        },
        {
          "id": "wednesday-2-142",
          "startTime": "8:00 PM",
          "endTime": "9:30 PM",
          "title": "Pickleball Open Play: NR/2.0-2.5 DUPR Optional",
          "subtitle": "Skill Level: 2.0-",
          "location": "Indoor Pickleball Courts"
        },
        {
          "id": "wednesday-2-143",
          "startTime": "9:30 PM",
          "endTime": "11:29 PM",
          "title": "Pickleball Open Play: 4.0-4.5 (80%+ Reliability Required) DUPR Optional",
          "subtitle": "Skill Level: 4.0-",
          "location": "Indoor Pickleball Courts"
        },
        {
          "id": "wednesday-2-144",
          "startTime": "9:30 PM",
          "endTime": "11:30 PM",
          "title": "Pickleball Open Play: 3.0-3.5 DUPR Optional",
          "subtitle": "Skill Level: 3.0-",
          "location": "Indoor Pickleball Courts"
        },
        {
          "id": "wednesday-2-145",
          "startTime": "9:30 PM",
          "endTime": "11:30 PM",
          "title": "Pickleball Open Play: 3.25-3.75 DUPR Optional",
          "subtitle": "Skill Level: 3.25-",
          "location": "Indoor Pickleball Courts"
        },
        {
          "id": "wednesday-2-146",
          "startTime": "9:30 PM",
          "endTime": "11:30 PM",
          "title": "Pickleball Open Play: 4.5+ DUPR Optional",
          "subtitle": "Skill Level: 4.5+",
          "location": "Indoor Pickleball Courts"
        },
        {
          "id": "wednesday-2-147",
          "startTime": "9:30 PM",
          "endTime": "11:30 PM",
          "title": "Pickleball Open Play: All Levels- 4 on/ 4 off",
          "subtitle": "Skill Level: All Levels",
          "location": "Indoor Pickleball Courts"
        }
      ],
      "header": "WEDNESDAY 2"
    },
    {
      "name": "THURSDAY",
      "date": 3,
      "highlight": false,
      "sessions": [
        {
          "id": "thursday-3-148",
          "startTime": "6:30 AM",
          "endTime": "8:00 AM",
          "title": "Pickleball Open Play: All Levels Drill Session: Bring Your Own Partner",
          "subtitle": "Skill Level: All Levels",
          "location": "Indoor Pickleball Courts"
        },
        {
          "id": "thursday-3-149",
          "startTime": "6:30 AM",
          "endTime": "8:00 AM",
          "title": "Pickleball Open Play: All Levels DUPR Optional",
          "subtitle": "Skill Level: All Levels",
          "location": "Indoor Pickleball Courts"
        },
        {
          "id": "thursday-3-150",
          "startTime": "8:00 AM",
          "endTime": "9:30 AM",
          "title": "Pickleball Open Play: All Levels Drill Session: Bring Your Own Partner",
          "subtitle": "Skill Level: All Levels",
          "location": "Indoor Pickleball Courts"
        },
        {
          "id": "thursday-3-151",
          "startTime": "8:00 AM",
          "endTime": "9:30 AM",
          "title": "Pickleball Open Play: All Levels DUPR Optional",
          "subtitle": "Skill Level: All Levels",
          "location": "Indoor Pickleball Courts"
        },
        {
          "id": "thursday-3-152",
          "startTime": "8:00 AM",
          "endTime": "10:00 AM",
          "title": "Pickleball Open Play: 4.0+ DUPR Optional",
          "subtitle": "Skill Level: 4.0+",
          "location": "Indoor Pickleball Courts"
        },
        {
          "id": "thursday-3-153",
          "startTime": "9:30 AM",
          "endTime": "11:30 AM",
          "title": "Pickleball Open Play: 3.0-3.75 DUPR Optional",
          "subtitle": "Skill Level: 3.0-",
          "location": "Indoor Pickleball Courts"
        },
        {
          "id": "thursday-3-154",
          "startTime": "9:30 AM",
          "endTime": "11:30 AM",
          "title": "Pickleball Open Play: 3.75-4.25 DUPR Optional",
          "subtitle": "Skill Level: 3.75-",
          "location": "Indoor Pickleball Courts"
        },
        {
          "id": "thursday-3-155",
          "startTime": "9:30 AM",
          "endTime": "11:30 AM",
          "title": "Pickleball Open Play: All Levels DUPR Optional",
          "subtitle": "Skill Level: All Levels",
          "location": "Indoor Pickleball Courts"
        },
        {
          "id": "thursday-3-156",
          "startTime": "9:30 AM",
          "endTime": "11:30 AM",
          "title": "Pickleball Open Play: Womens 2.0+ DUPR Optional",
          "subtitle": "Skill Level: 2.0+",
          "location": "Indoor Pickleball Courts"
        },
        {
          "id": "thursday-3-157",
          "startTime": "11:00 AM",
          "endTime": "1:00 PM",
          "title": "Pickleball Open Play: 3.5-4.0 DUPR Optional",
          "subtitle": "Skill Level: 3.5-",
          "location": "Indoor Pickleball Courts"
        },
        {
          "id": "thursday-3-158",
          "startTime": "11:30 AM",
          "endTime": "1:30 PM",
          "title": "Pickleball Open Play: Womens All Levels DUPR Optional",
          "subtitle": "Skill Level: All Levels",
          "location": "Indoor Pickleball Courts"
        },
        {
          "id": "thursday-3-159",
          "startTime": "12:00 PM",
          "endTime": "1:30 PM",
          "title": "Pickleball Open Play: Singles(1v1) All Levels DUPR Optional",
          "subtitle": "Skill Level: All Levels",
          "location": "Indoor Pickleball Courts"
        },
        {
          "id": "thursday-3-160",
          "startTime": "12:00 PM",
          "endTime": "2:00 PM",
          "title": "Pickleball Open Play: NR/2.0-3.0 DUPR Optional",
          "subtitle": "Skill Level: 2.0-",
          "location": "Indoor Pickleball Courts"
        },
        {
          "id": "thursday-3-161",
          "startTime": "12:30 PM",
          "endTime": "2:30 PM",
          "title": "Pickleball Open Play: All Levels (4on/4off) DUPR Optional",
          "subtitle": "Skill Level: All Levels",
          "location": "Indoor Pickleball Courts"
        },
        {
          "id": "thursday-3-162",
          "startTime": "1:30 PM",
          "endTime": "3:30 PM",
          "title": "Pickleball Open Play: 4.5+ DUPR Optional",
          "subtitle": "Skill Level: 4.5+",
          "location": "Indoor Pickleball Courts"
        },
        {
          "id": "thursday-3-163",
          "startTime": "1:30 PM",
          "endTime": "3:30 PM",
          "title": "Pickleball Open Play: 4.75+ DUPR Optional",
          "subtitle": "Skill Level: 4.75+",
          "location": "Indoor Pickleball Courts"
        },
        {
          "id": "thursday-3-164",
          "startTime": "2:00 PM",
          "endTime": "4:00 PM",
          "title": "Pickleball Open Play: All Levels (4on/4off) DUPR Optional",
          "subtitle": "Skill Level: All Levels",
          "location": "Indoor Pickleball Courts"
        },
        {
          "id": "thursday-3-165",
          "startTime": "3:00 PM",
          "endTime": "5:00 PM",
          "title": "Pickleball Open Play: 2.75-3.25 DUPR Mandatory: Club Submit",
          "subtitle": "Skill Level: 2.75-",
          "location": "Indoor Pickleball Courts"
        },
        {
          "id": "thursday-3-166",
          "startTime": "3:30 PM",
          "endTime": "5:30 PM",
          "title": "Pickleball Open Play: 3.75-4.25 (80%+ Reliability Required) DUPR Optional",
          "subtitle": "Skill Level: 3.75-",
          "location": "Indoor Pickleball Courts"
        },
        {
          "id": "thursday-3-167",
          "startTime": "5:30 PM",
          "endTime": "7:00 PM",
          "title": "Pickleball Open Play: 3.75+ (80%+ Reliability Required) DUPR Optional",
          "subtitle": "Skill Level: 3.75+",
          "location": "Indoor Pickleball Courts"
        },
        {
          "id": "thursday-3-168",
          "startTime": "5:30 PM",
          "endTime": "7:30 PM",
          "title": "Pickleball Open Play: 5.0+ DUPR Optional",
          "subtitle": "Skill Level: 5.0+",
          "location": "Indoor Pickleball Courts"
        },
        {
          "id": "thursday-3-169",
          "startTime": "6:00 PM",
          "endTime": "8:00 PM",
          "title": "Pickleball Open Play: All Levels, 8ppl, 4 on-4 off",
          "subtitle": "Skill Level: All Levels",
          "location": "Indoor Pickleball Courts"
        },
        {
          "id": "thursday-3-170",
          "startTime": "7:00 PM",
          "endTime": "9:00 PM",
          "title": "Pickleball Open Play: All Levels (4on/4off) DUPR Optional",
          "subtitle": "Skill Level: All Levels",
          "location": "Indoor Pickleball Courts"
        },
        {
          "id": "thursday-3-171",
          "startTime": "7:30 PM",
          "endTime": "9:30 PM",
          "title": "Pickleball Open Play: 3.0-3.5 (80%+ Reliability Required) DUPR Optional",
          "subtitle": "Skill Level: 3.0-",
          "location": "Indoor Pickleball Courts"
        },
        {
          "id": "thursday-3-172",
          "startTime": "7:30 PM",
          "endTime": "9:30 PM",
          "title": "Pickleball Open Play: 4.0+ 80+ reliability- DUPR Optional",
          "subtitle": "Skill Level: 4.0+",
          "location": "Indoor Pickleball Courts"
        },
        {
          "id": "thursday-3-173",
          "startTime": "8:00 PM",
          "endTime": "10:00 PM",
          "title": "Pickleball Open Play: All Levels, 8ppl, 4 on-4 off",
          "subtitle": "Skill Level: All Levels",
          "location": "Indoor Pickleball Courts"
        },
        {
          "id": "thursday-3-174",
          "startTime": "8:30 PM",
          "endTime": "9:29 PM",
          "title": "Pickleball Open Play",
          "location": "Indoor Pickleball Courts"
        },
        {
          "id": "thursday-3-175",
          "startTime": "9:30 PM",
          "endTime": "11:30 PM",
          "title": "Pickleball Open Play: 4.0+ DUPR Optional",
          "subtitle": "Skill Level: 4.0+",
          "location": "Indoor Pickleball Courts"
        },
        {
          "id": "thursday-3-176",
          "startTime": "9:30 PM",
          "endTime": "11:30 PM",
          "title": "Pickleball Open Play: 4.5+ DUPR Optional",
          "subtitle": "Skill Level: 4.5+",
          "location": "Indoor Pickleball Courts"
        },
        {
          "id": "thursday-3-177",
          "startTime": "10:00 PM",
          "endTime": "11:30 PM",
          "title": "Pickleball Open Play: 3.0-3.75 DUPR Optional",
          "subtitle": "Skill Level: 3.0-",
          "location": "Indoor Pickleball Courts"
        },
        {
          "id": "thursday-3-178",
          "startTime": "10:00 PM",
          "endTime": "11:30 PM",
          "title": "Pickleball Open Play: 3.75-4.75 DUPR Optional",
          "subtitle": "Skill Level: 3.75-",
          "location": "Indoor Pickleball Courts"
        },
        {
          "id": "thursday-3-179",
          "startTime": "10:00 PM",
          "endTime": "11:30 PM",
          "title": "Pickleball Open Play: All Levels (4on4off) DUPR Optional",
          "subtitle": "Skill Level: All Levels",
          "location": "Indoor Pickleball Courts"
        }
      ],
      "header": "THURSDAY 3"
    },
    {
      "name": "FRIDAY",
      "date": 4,
      "highlight": false,
      "sessions": [
        {
          "id": "friday-4-180",
          "startTime": "6:30 AM",
          "endTime": "8:00 AM",
          "title": "Pickleball Open Play: 3.0+ DUPR Optional",
          "subtitle": "Skill Level: 3.0+",
          "location": "Indoor Pickleball Courts"
        },
        {
          "id": "friday-4-181",
          "startTime": "6:30 AM",
          "endTime": "8:00 AM",
          "title": "Pickleball Open Play: All Levels Drill Session: Bring Your Own Partner",
          "subtitle": "Skill Level: All Levels",
          "location": "Indoor Pickleball Courts"
        },
        {
          "id": "friday-4-182",
          "startTime": "6:30 AM",
          "endTime": "8:00 AM",
          "title": "Pickleball Open Play: All Levels DUPR Optional",
          "subtitle": "Skill Level: All Levels",
          "location": "Indoor Pickleball Courts"
        },
        {
          "id": "friday-4-183",
          "startTime": "8:00 AM",
          "endTime": "9:30 AM",
          "title": "Pickleball Open Play: All Levels Drill Session: Bring Your Own Partner",
          "subtitle": "Skill Level: All Levels",
          "location": "Indoor Pickleball Courts"
        },
        {
          "id": "friday-4-184",
          "startTime": "8:00 AM",
          "endTime": "9:30 AM",
          "title": "Pickleball Open Play: All Levels DUPR Optional (4on/4off)",
          "subtitle": "Skill Level: All Levels",
          "location": "Indoor Pickleball Courts"
        },
        {
          "id": "friday-4-185",
          "startTime": "8:00 AM",
          "endTime": "10:00 AM",
          "title": "Pickleball Open Play: 4.0+ DUPR Optional",
          "subtitle": "Skill Level: 4.0+",
          "location": "Indoor Pickleball Courts"
        },
        {
          "id": "friday-4-186",
          "startTime": "8:00 AM",
          "endTime": "10:00 AM",
          "title": "Pickleball Open Play: Womens 3.25+(80% Reliability) DUPR Optional",
          "subtitle": "Skill Level: 3.25+",
          "location": "Indoor Pickleball Courts"
        },
        {
          "id": "friday-4-187",
          "startTime": "9:30 AM",
          "endTime": "11:30 AM",
          "title": "Pickleball Open Play: Womens NR/2.0+ DUPR Optional",
          "subtitle": "Skill Level: 2.0+",
          "location": "Indoor Pickleball Courts"
        },
        {
          "id": "friday-4-188",
          "startTime": "10:00 AM",
          "endTime": "11:30 AM",
          "title": "Pickleball Open Play: 3.75-4.25 DUPR Optional",
          "subtitle": "Skill Level: 3.75-",
          "location": "Indoor Pickleball Courts"
        },
        {
          "id": "friday-4-189",
          "startTime": "10:00 AM",
          "endTime": "12:00 PM",
          "title": "Pickleball Open Play: All Levels (4on4off) DUPR Optional",
          "subtitle": "Skill Level: All Levels",
          "location": "Indoor Pickleball Courts"
        },
        {
          "id": "friday-4-190",
          "startTime": "11:30 AM",
          "endTime": "1:00 PM",
          "title": "Pickleball Open Play: 3.0-3.5 DUPR Optional",
          "subtitle": "Skill Level: 3.0-",
          "location": "Indoor Pickleball Courts"
        },
        {
          "id": "friday-4-191",
          "startTime": "11:30 AM",
          "endTime": "1:00 PM",
          "title": "Pickleball Open Play: 3.75-4.25 DUPR Optional",
          "subtitle": "Skill Level: 3.75-",
          "location": "Indoor Pickleball Courts"
        },
        {
          "id": "friday-4-192",
          "startTime": "11:30 AM",
          "endTime": "1:30 PM",
          "title": "Pickleball Open Play: NR/2.0-3.0 DUPR Optional",
          "subtitle": "Skill Level: 2.0-",
          "location": "Indoor Pickleball Courts"
        },
        {
          "id": "friday-4-193",
          "startTime": "12:00 PM",
          "endTime": "1:30 PM",
          "title": "Pickleball Open Play: 4.75+ Drill Session: Bring Your Own Partner",
          "subtitle": "Skill Level: 4.75+",
          "location": "Indoor Pickleball Courts"
        },
        {
          "id": "friday-4-194",
          "startTime": "1:00 PM",
          "endTime": "2:30 PM",
          "title": "Pickleball Open Play: 3.25-3.75 DUPR Optional",
          "subtitle": "Skill Level: 3.25-",
          "location": "Indoor Pickleball Courts"
        },
        {
          "id": "friday-4-195",
          "startTime": "1:00 PM",
          "endTime": "2:30 PM",
          "title": "Pickleball Open Play: 3.5-4.0 DUPR Optional",
          "subtitle": "Skill Level: 3.5-",
          "location": "Indoor Pickleball Courts"
        },
        {
          "id": "friday-4-196",
          "startTime": "1:30 PM",
          "endTime": "3:30 PM",
          "title": "Pickleball Open Play: 4.25+ DUPR Optional",
          "subtitle": "Skill Level: 4.25+",
          "location": "Indoor Pickleball Courts"
        },
        {
          "id": "friday-4-197",
          "startTime": "1:30 PM",
          "endTime": "3:30 PM",
          "title": "Pickleball Open Play: 4.75+ DUPR Optional",
          "subtitle": "Skill Level: 4.75+",
          "location": "Indoor Pickleball Courts"
        },
        {
          "id": "friday-4-198",
          "startTime": "2:00 PM",
          "endTime": "3:30 PM",
          "title": "Pickleball Open Play: 2.75-3.25 DUPR Optional",
          "subtitle": "Skill Level: 2.75-",
          "location": "Indoor Pickleball Courts"
        },
        {
          "id": "friday-4-199",
          "startTime": "3:30 PM",
          "endTime": "5:00 PM",
          "title": "Pickleball Open Play: 4.25+ (80%+ Reliability Score Required) DUPR Optional",
          "subtitle": "Skill Level: 4.25+",
          "location": "Indoor Pickleball Courts"
        },
        {
          "id": "friday-4-200",
          "startTime": "3:30 PM",
          "endTime": "5:00 PM",
          "title": "Pickleball Open Play: All Levels (4on/4off) DUPR Optional",
          "subtitle": "Skill Level: All Levels",
          "location": "Indoor Pickleball Courts"
        },
        {
          "id": "friday-4-201",
          "startTime": "3:30 PM",
          "endTime": "5:30 PM",
          "title": "Pickleball Open Play: 3.75-4.25 (80%+ Reliability Score Required) DUPR Optional",
          "subtitle": "Skill Level: 3.75-",
          "location": "Indoor Pickleball Courts"
        },
        {
          "id": "friday-4-202",
          "startTime": "4:30 PM",
          "endTime": "6:30 PM",
          "title": "Pickleball Open Play: 3.5-4.0 (80%+ Reliability Score Required) DUPR Optional",
          "subtitle": "Skill Level: 3.5-",
          "location": "Indoor Pickleball Courts"
        },
        {
          "id": "friday-4-203",
          "startTime": "5:00 PM",
          "endTime": "6:30 PM",
          "title": "Pickleball Open Play: 3.0-3.5 DUPR Mandatory: Club Submit",
          "subtitle": "Skill Level: 3.0-",
          "location": "Indoor Pickleball Courts"
        },
        {
          "id": "friday-4-204",
          "startTime": "5:00 PM",
          "endTime": "7:00 PM",
          "title": "Pickleball Open Play: 4.0-4.5 BYOP (Combine <9.1) DUPR Mandatory: Club Submit (Partners Stay)",
          "subtitle": "Skill Level: 4.0-",
          "location": "Indoor Pickleball Courts"
        },
        {
          "id": "friday-4-205",
          "startTime": "5:30 PM",
          "endTime": "7:00 PM",
          "title": "Pickleball Open Play: 2.5-3.0 DUPR Mandatory: Club Submit",
          "subtitle": "Skill Level: 2.5-",
          "location": "Indoor Pickleball Courts"
        },
        {
          "id": "friday-4-206",
          "startTime": "5:30 PM",
          "endTime": "7:00 PM",
          "title": "Pickleball Open Play: Womens 3.50+ (80%+ Reliability Score) DUPR Optional",
          "subtitle": "Skill Level: 3.50+",
          "location": "Indoor Pickleball Courts"
        },
        {
          "id": "friday-4-207",
          "startTime": "6:30 PM",
          "endTime": "8:00 PM",
          "title": "Pickleball Open Play: NR/2.0-2.5 DUPR Mandatory: Club Submit",
          "subtitle": "Skill Level: 2.0-",
          "location": "Indoor Pickleball Courts"
        },
        {
          "id": "friday-4-208",
          "startTime": "6:30 PM",
          "endTime": "8:30 PM",
          "title": "Pickleball Open Play: All Levels (4on/4off) DUPR Optional",
          "subtitle": "Skill Level: All Levels",
          "location": "Indoor Pickleball Courts"
        },
        {
          "id": "friday-4-209",
          "startTime": "7:00 PM",
          "endTime": "9:00 PM",
          "title": "Pickleball Open Play: 3.75-4.25 BYOP (Combine <8.6) DUPR Mandatory: Club Submit (Partners Stay)",
          "subtitle": "Skill Level: 3.75-",
          "location": "Indoor Pickleball Courts"
        },
        {
          "id": "friday-4-210",
          "startTime": "8:00 PM",
          "endTime": "9:30 PM",
          "title": "Pickleball Open Play: 2.75-3.25 DUPR Mandatory: Club Submit",
          "subtitle": "Skill Level: 2.75-",
          "location": "Indoor Pickleball Courts"
        },
        {
          "id": "friday-4-211",
          "startTime": "9:30 PM",
          "endTime": "11:30 PM",
          "title": "Pickleball Open Play: 3.25+ DUPR Optional",
          "subtitle": "Skill Level: 3.25+",
          "location": "Indoor Pickleball Courts"
        },
        {
          "id": "friday-4-212",
          "startTime": "9:30 PM",
          "endTime": "11:30 PM",
          "title": "Pickleball Open Play: All Levels (4on4off) DUPR Optional",
          "subtitle": "Skill Level: All Levels",
          "location": "Indoor Pickleball Courts"
        }
      ],
      "header": "FRIDAY 4"
    },
    {
      "name": "SATURDAY",
      "date": 5,
      "highlight": false,
      "sessions": [
        {
          "id": "saturday-5-213",
          "startTime": "7:00 AM",
          "endTime": "8:30 AM",
          "title": "Pickleball Open Play: All Levels Drill Session: Bring Your Own Partner",
          "subtitle": "Skill Level: All Levels",
          "location": "Indoor Pickleball Courts"
        }
      ],
      "header": "SATURDAY 5"
    },
    {
      "name": "SUNDAY",
      "date": 30,
      "highlight": false,
      "sessions": [
        {
          "id": "sunday-30-0",
          "startTime": "7:00 AM",
          "endTime": "8:30 AM",
          "title": "Pickleball Open Play: All Levels Drill Session: Bring Your Own Partner",
          "subtitle": "Skill Level: All Levels",
          "location": "Indoor Pickleball Courts"
        },
        {
          "id": "sunday-30-1",
          "startTime": "8:30 AM",
          "endTime": "10:30 AM",
          "title": "Pickleball Open Play: 2.75-3.25 DUPR Optional",
          "subtitle": "Skill Level: 2.75-",
          "location": "Indoor Pickleball Courts"
        },
        {
          "id": "sunday-30-2",
          "startTime": "8:30 AM",
          "endTime": "10:30 AM",
          "title": "Pickleball Open Play: 4.25+ (80%+ Reliability Required) DUPR Optional",
          "subtitle": "Skill Level: 4.25+",
          "location": "Indoor Pickleball Courts"
        },
        {
          "id": "sunday-30-3",
          "startTime": "8:30 AM",
          "endTime": "10:30 AM",
          "title": "Pickleball Open Play: All Levels (4on4off) DUPR Optional",
          "subtitle": "Skill Level: All Levels",
          "location": "Indoor Pickleball Courts"
        },
        {
          "id": "sunday-30-4",
          "startTime": "8:30 AM",
          "endTime": "10:30 AM",
          "title": "Pickleball Open Play: NR/2.0-2.75 DUPR Optional",
          "subtitle": "Skill Level: 2.0-",
          "location": "Indoor Pickleball Courts"
        },
        {
          "id": "sunday-30-5",
          "startTime": "10:30 AM",
          "endTime": "12:30 PM",
          "title": "Pickleball Open Play: 3.25-4.25 (League Sub) DUPR Mandatory: Club Submit",
          "subtitle": "Skill Level: 3.25-",
          "location": "Indoor Pickleball Courts"
        },
        {
          "id": "sunday-30-6",
          "startTime": "12:30 PM",
          "endTime": "2:30 PM",
          "title": "Pickleball Open Play: All Levels (4on4off) DUPR Optional",
          "subtitle": "Skill Level: All Levels",
          "location": "Indoor Pickleball Courts"
        },
        {
          "id": "sunday-30-7",
          "startTime": "12:30 PM",
          "endTime": "2:30 PM",
          "title": "Pickleball Open Play: Womens 3.25-3.75 (80%+ Reliability Required) DUPR Optional",
          "subtitle": "Skill Level: 3.25-",
          "location": "Indoor Pickleball Courts"
        },
        {
          "id": "sunday-30-8",
          "startTime": "1:00 PM",
          "endTime": "2:30 PM",
          "title": "Pickleball Open Play: 4.0-4.5 (80%+ Reliability Required) DUPR Optional",
          "subtitle": "Skill Level: 4.0-",
          "location": "Indoor Pickleball Courts"
        },
        {
          "id": "sunday-30-9",
          "startTime": "1:00 PM",
          "endTime": "2:30 PM",
          "title": "Pickleball Open Play: 4.5+ (80%+ Reliability Required) DUPR Optional",
          "subtitle": "Skill Level: 4.5+",
          "location": "Indoor Pickleball Courts"
        },
        {
          "id": "sunday-30-10",
          "startTime": "1:00 PM",
          "endTime": "2:30 PM",
          "title": "Pickleball Open Play: Women's 3.75+ (80%+ Reliability Required) DUPR Optional",
          "subtitle": "Skill Level: 3.75+",
          "location": "Indoor Pickleball Courts"
        },
        {
          "id": "sunday-30-11",
          "startTime": "2:30 PM",
          "endTime": "4:00 PM",
          "title": "Pickleball Open Play: Singles(1v1) 3.0-3.5 DUPR Mandatory: Club Submit",
          "subtitle": "Skill Level: 3.0-",
          "location": "Indoor Pickleball Courts"
        },
        {
          "id": "sunday-30-12",
          "startTime": "2:30 PM",
          "endTime": "4:00 PM",
          "title": "Pickleball Open Play: Singles(1v1) 3.5-4.0 DUPR Mandatory: Club Submit",
          "subtitle": "Skill Level: 3.5-",
          "location": "Indoor Pickleball Courts"
        },
        {
          "id": "sunday-30-13",
          "startTime": "2:30 PM",
          "endTime": "4:00 PM",
          "title": "Pickleball Open Play: Singles(1v1) 4.0-4.5 DUPR Mandatory: Club Submit",
          "subtitle": "Skill Level: 4.0-",
          "location": "Indoor Pickleball Courts"
        },
        {
          "id": "sunday-30-14",
          "startTime": "2:30 PM",
          "endTime": "4:00 PM",
          "title": "Pickleball Open Play: Singles(1v1) 4.5+ DUPR Optional",
          "subtitle": "Skill Level: 4.5+",
          "location": "Indoor Pickleball Courts"
        },
        {
          "id": "sunday-30-15",
          "startTime": "2:30 PM",
          "endTime": "4:00 PM",
          "title": "Pickleball Open Play: Singles(1v1) All Levels DUPR Optional",
          "subtitle": "Skill Level: All Levels",
          "location": "Indoor Pickleball Courts"
        },
        {
          "id": "sunday-30-16",
          "startTime": "2:30 PM",
          "endTime": "4:00 PM",
          "title": "Pickleball Open Play: Womens Singles(1v1) All Levels DUPR Optional",
          "subtitle": "Skill Level: All Levels",
          "location": "Indoor Pickleball Courts"
        },
        {
          "id": "sunday-30-17",
          "startTime": "4:00 PM",
          "endTime": "6:00 PM",
          "title": "Pickleball Open Play: 3.75-4.25 (80%+ Reliability Required) DUPR Optional",
          "subtitle": "Skill Level: 3.75-",
          "location": "Indoor Pickleball Courts"
        },
        {
          "id": "sunday-30-18",
          "startTime": "4:00 PM",
          "endTime": "6:00 PM",
          "title": "Pickleball Open Play: 4.0-4.5 (80%+ Reliability Required) DUPR Optional",
          "subtitle": "Skill Level: 4.0-",
          "location": "Indoor Pickleball Courts"
        },
        {
          "id": "sunday-30-19",
          "startTime": "4:00 PM",
          "endTime": "6:00 PM",
          "title": "Pickleball Open Play: 4.25-4.75 (80%+ Reliability Required) DUPR Optional",
          "subtitle": "Skill Level: 4.25-",
          "location": "Indoor Pickleball Courts"
        },
        {
          "id": "sunday-30-20",
          "startTime": "4:00 PM",
          "endTime": "6:00 PM",
          "title": "Pickleball Open Play: All Levels (4on4off) DUPR Optional",
          "subtitle": "Skill Level: All Levels",
          "location": "Indoor Pickleball Courts"
        },
        {
          "id": "sunday-30-21",
          "startTime": "6:00 PM",
          "endTime": "8:00 PM",
          "title": "Pickleball Open Play: 3.5-4.0 DUPR Optional",
          "subtitle": "Skill Level: 3.5-",
          "location": "Indoor Pickleball Courts"
        },
        {
          "id": "sunday-30-22",
          "startTime": "6:00 PM",
          "endTime": "8:00 PM",
          "title": "Pickleball Open Play: 4.5-5.0 DUPR Optional",
          "subtitle": "Skill Level: 4.5-",
          "location": "Indoor Pickleball Courts"
        },
        {
          "id": "sunday-30-23",
          "startTime": "6:00 PM",
          "endTime": "8:00 PM",
          "title": "Pickleball Open Play: NR/2.0-3.0 DUPR Optional",
          "subtitle": "Skill Level: 2.0-",
          "location": "Indoor Pickleball Courts"
        },
        {
          "id": "sunday-30-24",
          "startTime": "7:00 PM",
          "endTime": "9:00 PM",
          "title": "Pickleball Open Play: 3.0-3.5 DUPR Optional",
          "subtitle": "Skill Level: 3.0-",
          "location": "Indoor Pickleball Courts"
        },
        {
          "id": "sunday-30-25",
          "startTime": "7:00 PM",
          "endTime": "9:00 PM",
          "title": "Pickleball Open Play: 4.0-4.5 DUPR Optional",
          "subtitle": "Skill Level: 4.0-",
          "location": "Indoor Pickleball Courts"
        },
        {
          "id": "sunday-30-26",
          "startTime": "9:00 PM",
          "endTime": "10:30 PM",
          "title": "Pickleball Open Play: 2.75-3.25 DUPR Optional",
          "subtitle": "Skill Level: 2.75-",
          "location": "Indoor Pickleball Courts"
        },
        {
          "id": "sunday-30-27",
          "startTime": "9:00 PM",
          "endTime": "10:30 PM",
          "title": "Pickleball Open Play: All Levels (4on4off) DUPR Optional",
          "subtitle": "Skill Level: All Levels",
          "location": "Indoor Pickleball Courts"
        },
        {
          "id": "sunday-30-28",
          "startTime": "9:00 PM",
          "endTime": "10:30 PM",
          "title": "Pickleball Open Play: All Levels Drill Session: Bring Your Own Partner",
          "subtitle": "Skill Level: All Levels",
          "location": "Indoor Pickleball Courts"
        }
      ],
      "header": "SUNDAY 30"
    },
    {
      "name": "MONDAY",
      "date": 31,
      "highlight": false,
      "sessions": [
        {
          "id": "monday-31-29",
          "startTime": "6:30 AM",
          "endTime": "8:00 AM",
          "title": "Pickleball Open Play",
          "location": "Indoor Pickleball Courts"
        },
        {
          "id": "monday-31-30",
          "startTime": "6:30 AM",
          "endTime": "8:00 AM",
          "title": "Pickleball Open Play: All Levels Open Play DUPR Optional (4on/4off)",
          "subtitle": "Skill Level: All Levels",
          "location": "Indoor Pickleball Courts"
        },
        {
          "id": "monday-31-31",
          "startTime": "8:00 AM",
          "endTime": "9:30 AM",
          "title": "Pickleball Open Play: All Levels Drill Session: Bring Your Own Partner",
          "subtitle": "Skill Level: All Levels",
          "location": "Indoor Pickleball Courts"
        },
        {
          "id": "monday-31-32",
          "startTime": "8:00 AM",
          "endTime": "10:00 AM",
          "title": "Pickleball Open Play: All Levels DUPR Optional",
          "subtitle": "Skill Level: All Levels",
          "location": "Indoor Pickleball Courts"
        },
        {
          "id": "monday-31-33",
          "startTime": "9:30 AM",
          "endTime": "11:30 AM",
          "title": "Pickleball Open Play: 3.75-4.25 DUPR Optional",
          "subtitle": "Skill Level: 3.75-",
          "location": "Indoor Pickleball Courts"
        },
        {
          "id": "monday-31-34",
          "startTime": "9:30 AM",
          "endTime": "11:30 AM",
          "title": "Pickleball Open Play: All Levels (4on/off) DUPR Optional",
          "subtitle": "Skill Level: All Levels",
          "location": "Indoor Pickleball Courts"
        },
        {
          "id": "monday-31-35",
          "startTime": "9:30 AM",
          "endTime": "11:30 AM",
          "title": "Pickleball Open Play: Womens 2.0+ DUPR Optional",
          "subtitle": "Skill Level: 2.0+",
          "location": "Indoor Pickleball Courts"
        },
        {
          "id": "monday-31-36",
          "startTime": "10:00 AM",
          "endTime": "11:30 AM",
          "title": "Pickleball Open Play: 3.25-3.75 DUPR Optional",
          "subtitle": "Skill Level: 3.25-",
          "location": "Indoor Pickleball Courts"
        },
        {
          "id": "monday-31-37",
          "startTime": "10:00 AM",
          "endTime": "12:00 PM",
          "title": "Pickleball Open Play: 2.75-3.25 DUPR Mandatory: Club Submit",
          "subtitle": "Skill Level: 2.75-",
          "location": "Indoor Pickleball Courts"
        },
        {
          "id": "monday-31-38",
          "startTime": "10:00 AM",
          "endTime": "12:00 PM",
          "title": "Pickleball Open Play: NR/2.0-2.75 DUPR Mandatory-Club Submit",
          "subtitle": "Skill Level: 2.0-",
          "location": "Indoor Pickleball Courts"
        },
        {
          "id": "monday-31-39",
          "startTime": "11:30 AM",
          "endTime": "1:30 PM",
          "title": "Pickleball Open Play: 3.0-3.5 DUPR Optional",
          "subtitle": "Skill Level: 3.0-",
          "location": "Indoor Pickleball Courts"
        },
        {
          "id": "monday-31-40",
          "startTime": "11:30 AM",
          "endTime": "1:30 PM",
          "title": "Pickleball Open Play: 3.75-4.25 DUPR Optional",
          "subtitle": "Skill Level: 3.75-",
          "location": "Indoor Pickleball Courts"
        },
        {
          "id": "monday-31-41",
          "startTime": "11:30 AM",
          "endTime": "1:30 PM",
          "title": "Pickleball Open Play: 4.0+ DUPR Optional",
          "subtitle": "Skill Level: 4.0+",
          "location": "Indoor Pickleball Courts"
        },
        {
          "id": "monday-31-42",
          "startTime": "12:00 PM",
          "endTime": "2:00 PM",
          "title": "Pickleball Open Play: All Levels (4on4off) DUPR Optional",
          "subtitle": "Skill Level: All Levels",
          "location": "Indoor Pickleball Courts"
        },
        {
          "id": "monday-31-43",
          "startTime": "1:30 PM",
          "endTime": "3:30 PM",
          "title": "Pickleball Open Play: 3.25-3.75 DUPR Optional",
          "subtitle": "Skill Level: 3.25-",
          "location": "Indoor Pickleball Courts"
        },
        {
          "id": "monday-31-44",
          "startTime": "1:30 PM",
          "endTime": "3:30 PM",
          "title": "Pickleball Open Play: 4.5+ DUPR Optional",
          "subtitle": "Skill Level: 4.5+",
          "location": "Indoor Pickleball Courts"
        },
        {
          "id": "monday-31-45",
          "startTime": "1:30 PM",
          "endTime": "3:30 PM",
          "title": "Pickleball Open Play: 4.75+ DUPR Optional",
          "subtitle": "Skill Level: 4.75+",
          "location": "Indoor Pickleball Courts"
        },
        {
          "id": "monday-31-46",
          "startTime": "1:30 PM",
          "endTime": "3:30 PM",
          "title": "Pickleball Open Play: All Levels (4on/4off) DUPR Optional",
          "subtitle": "Skill Level: All Levels",
          "location": "Indoor Pickleball Courts"
        },
        {
          "id": "monday-31-47",
          "startTime": "2:00 PM",
          "endTime": "3:30 PM",
          "title": "Pickleball Open Play: All Levels Drill Session: Bring Your Own Partner",
          "subtitle": "Skill Level: All Levels",
          "location": "Indoor Pickleball Courts"
        },
        {
          "id": "monday-31-48",
          "startTime": "2:00 PM",
          "endTime": "4:00 PM",
          "title": "Pickleball Open Play: NR/2.0-3.0 DUPR Optional",
          "subtitle": "Skill Level: 2.0-",
          "location": "Indoor Pickleball Courts"
        },
        {
          "id": "monday-31-49",
          "startTime": "3:30 PM",
          "endTime": "5:00 PM",
          "title": "Pickleball Open Play: 2.75-3.25 DUPR Optional",
          "subtitle": "Skill Level: 2.75-",
          "location": "Indoor Pickleball Courts"
        },
        {
          "id": "monday-31-50",
          "startTime": "3:30 PM",
          "endTime": "5:30 PM",
          "title": "Pickleball Open Play: 3.75-4.25 (80%+ Reliability Required) DUPR Optional",
          "subtitle": "Skill Level: 3.75-",
          "location": "Indoor Pickleball Courts"
        },
        {
          "id": "monday-31-51",
          "startTime": "3:30 PM",
          "endTime": "5:30 PM",
          "title": "Pickleball Open Play: All Levels DUPR Optional (4on/4off)",
          "subtitle": "Skill Level: All Levels",
          "location": "Indoor Pickleball Courts"
        },
        {
          "id": "monday-31-52",
          "startTime": "4:00 PM",
          "endTime": "6:00 PM",
          "title": "Pickleball Open Play: 3.5-4.0 (80%+ Reliability Required) DUPR Optional",
          "subtitle": "Skill Level: 3.5-",
          "location": "Indoor Pickleball Courts"
        },
        {
          "id": "monday-31-53",
          "startTime": "4:00 PM",
          "endTime": "6:00 PM",
          "title": "Pickleball Open Play: All Levels (4on4off) DUPR Optional",
          "subtitle": "Skill Level: All Levels",
          "location": "Indoor Pickleball Courts"
        },
        {
          "id": "monday-31-54",
          "startTime": "5:00 PM",
          "endTime": "6:30 PM",
          "title": "Pickleball Open Play: 4.0+ (80%+ Reliability Required) DUPR Optional",
          "subtitle": "Skill Level: 4.0+",
          "location": "Indoor Pickleball Courts"
        },
        {
          "id": "monday-31-55",
          "startTime": "5:30 PM",
          "endTime": "7:00 PM",
          "title": "Pickleball Open Play: Womens 3.0-3.75 (80% Reliability )   DUPR Optional",
          "subtitle": "Skill Level: 3.0-",
          "location": "Indoor Pickleball Courts"
        },
        {
          "id": "monday-31-56",
          "startTime": "6:00 PM",
          "endTime": "8:00 PM",
          "title": "Pickleball Open Play: 5.0+(80+ reliability) DUPR Optional",
          "subtitle": "Skill Level: 5.0+",
          "location": "Indoor Pickleball Courts"
        },
        {
          "id": "monday-31-57",
          "startTime": "6:00 PM",
          "endTime": "8:00 PM",
          "title": "Pickleball Open Play: NR/2.0-2.75 DUPR Optional",
          "subtitle": "Skill Level: 2.0-",
          "location": "Indoor Pickleball Courts"
        },
        {
          "id": "monday-31-58",
          "startTime": "6:30 PM",
          "endTime": "8:30 PM",
          "title": "Pickleball Open Play: Womens 3.5+ (80%+ Reliability Required) DUPR Optional",
          "subtitle": "Skill Level: 3.5+",
          "location": "Indoor Pickleball Courts"
        },
        {
          "id": "monday-31-59",
          "startTime": "7:00 PM",
          "endTime": "9:00 PM",
          "title": "Pickleball Open Play: 4.0-4.5 (80%+ Reliability Required) DUPR Optional",
          "subtitle": "Skill Level: 4.0-",
          "location": "Indoor Pickleball Courts"
        },
        {
          "id": "monday-31-60",
          "startTime": "8:00 PM",
          "endTime": "10:00 PM",
          "title": "Pickleball Open Play: 2.75-3.25 DUPR Mandatory; Club Submit",
          "subtitle": "Skill Level: 2.75-",
          "location": "Indoor Pickleball Courts"
        },
        {
          "id": "monday-31-61",
          "startTime": "8:00 PM",
          "endTime": "10:00 PM",
          "title": "Pickleball Open Play: 4.5+ DUPR Mandatory",
          "subtitle": "Skill Level: 4.5+",
          "location": "Indoor Pickleball Courts"
        },
        {
          "id": "monday-31-62",
          "startTime": "8:30 PM",
          "endTime": "10:30 PM",
          "title": "Pickleball Open Play: 4.75+ (80%+ Reliability Required) DUPR Optional",
          "subtitle": "Skill Level: 4.75+",
          "location": "Indoor Pickleball Courts"
        },
        {
          "id": "monday-31-63",
          "startTime": "9:00 PM",
          "endTime": "10:30 PM",
          "title": "Pickleball Open Play: 3.75-4.25 DUPR Optional (80% Reliability Required)",
          "subtitle": "Skill Level: 3.75-",
          "location": "Indoor Pickleball Courts"
        },
        {
          "id": "monday-31-64",
          "startTime": "10:00 PM",
          "endTime": "11:30 PM",
          "title": "Pickleball Open Play: All Levels (4on4off) DUPR Optional",
          "subtitle": "Skill Level: All Levels",
          "location": "Indoor Pickleball Courts"
        },
        {
          "id": "monday-31-65",
          "startTime": "10:30 PM",
          "endTime": "11:30 PM",
          "title": "Pickleball Open Play",
          "location": "Indoor Pickleball Courts"
        },
        {
          "id": "monday-31-66",
          "startTime": "10:30 PM",
          "endTime": "11:30 PM",
          "title": "Pickleball Open Play: 3.5+ DUPR Optional",
          "subtitle": "Skill Level: 3.5+",
          "location": "Indoor Pickleball Courts"
        },
        {
          "id": "monday-31-67",
          "startTime": "10:30 PM",
          "endTime": "11:30 PM",
          "title": "Pickleball Open Play: 4.0+ DUPR Optional",
          "subtitle": "Skill Level: 4.0+",
          "location": "Indoor Pickleball Courts"
        }
      ],
      "header": "MONDAY 31"
    }
  ],
  "_source": "github-actions-scraper",
  "_debug": {
    "serverTime": "2025-03-23T02:36:37.534Z",
    "calculatedNextSunday": "2025-03-30T02:36:37.534Z",
    "daysUntilNextSunday": 7
  }
}